solidity_merkletools/__init__.py
solidity_merkletools-0.0.2.dist-info/LICENSE
solidity_merkletools-0.0.2.dist-info/METADATA
solidity_merkletools-0.0.2.dist-info/WHEEL
solidity_merkletools-0.0.2.dist-info/top_level.txt
solidity_merkletools-0.0.2.dist-info/RECORD
